aws_secrets_loader/__init__.py
aws_secrets_loader/clients.py
aws_secrets_loader/loaders.py
aws_secrets_loader-0.1.1.dist-info/METADATA
aws_secrets_loader-0.1.1.dist-info/WHEEL
aws_secrets_loader-0.1.1.dist-info/RECORD
