Metadata-Version: 2.3
Name: aws-secrets-loader
Version: 0.1.1
Summary: 
Author: Alejandro Socorro
Author-email: alejandro.socorro@rakuten.com
Requires-Python: >=3.7,<4.0
Classifier: Programming Language :: Python :: 3
Classifier: Programming Language :: Python :: 3.7
Classifier: Programming Language :: Python :: 3.8
Classifier: Programming Language :: Python :: 3.9
Classifier: Programming Language :: Python :: 3.10
Classifier: Programming Language :: Python :: 3.11
Classifier: Programming Language :: Python :: 3.12
Classifier: Programming Language :: Python :: 3.13
Requires-Dist: boto3 (>=1.14.47,<2.0.0)
